pymodaq_plugins_redpitaya/__init__.py
pymodaq_plugins_redpitaya/utils.py
pymodaq_plugins_redpitaya/daq_move_plugins/__init__.py
pymodaq_plugins_redpitaya/daq_viewer_plugins/__init__.py
pymodaq_plugins_redpitaya/daq_viewer_plugins/plugins_0D/__init__.py
pymodaq_plugins_redpitaya/daq_viewer_plugins/plugins_1D/__init__.py
pymodaq_plugins_redpitaya/daq_viewer_plugins/plugins_1D/daq_1Dviewer_RedPitayaSCPI.py
pymodaq_plugins_redpitaya/daq_viewer_plugins/plugins_2D/__init__.py
pymodaq_plugins_redpitaya/daq_viewer_plugins/plugins_ND/__init__.py
pymodaq_plugins_redpitaya/exporters/__init__.py
pymodaq_plugins_redpitaya/extensions/__init__.py
pymodaq_plugins_redpitaya/extensions/myextension.py
pymodaq_plugins_redpitaya/hardware/__init__.py
pymodaq_plugins_redpitaya/models/PIDModelTemplate.py
pymodaq_plugins_redpitaya/models/__init__.py
pymodaq_plugins_redpitaya/resources/VERSION
pymodaq_plugins_redpitaya/resources/__init__.py
pymodaq_plugins_redpitaya/resources/config_template.toml
pymodaq_plugins_redpitaya/scanners/__init__.py
pymodaq_plugins_redpitaya-0.0.3.dist-info/LICENSE
pymodaq_plugins_redpitaya-0.0.3.dist-info/METADATA
pymodaq_plugins_redpitaya-0.0.3.dist-info/WHEEL
pymodaq_plugins_redpitaya-0.0.3.dist-info/entry_points.txt
pymodaq_plugins_redpitaya-0.0.3.dist-info/top_level.txt
pymodaq_plugins_redpitaya-0.0.3.dist-info/RECORD
