Metadata-Version: 2.1
Name: pymodaq-plugins-redpitaya
Version: 0.0.3
Summary: PyMoDAQ Plugin to use the Redpitaya electronic board
Home-page: https://github.com/PyMoDAQ/pymodaq_plugins_redpitaya
Author: Sebastien J. Weber
Author-email: sebastien.weber@cemes.fr
License: MIT
Classifier: Programming Language :: Python :: 3
Classifier: Development Status :: 5 - Production/Stable
Classifier: Environment :: Other Environment
Classifier: Intended Audience :: Science/Research
Classifier: Topic :: Scientific/Engineering :: Human Machine Interfaces
Classifier: Topic :: Scientific/Engineering :: Visualization
Classifier: License :: OSI Approved :: MIT License
Classifier: Operating System :: OS Independent
Classifier: Topic :: Software Development :: Libraries :: Python Modules
Classifier: Topic :: Software Development :: User Interfaces
License-File: LICENSE
Requires-Dist: toml
Requires-Dist: pymodaq >=4.1.0
Requires-Dist: pymeasure
